network_com/__init__.py
network_com/client.py
network_com/config.py
network_com/server.py
network_com-1.3.0.dist-info/LICENSE
network_com-1.3.0.dist-info/METADATA
network_com-1.3.0.dist-info/WHEEL
network_com-1.3.0.dist-info/entry_points.txt
network_com-1.3.0.dist-info/top_level.txt
network_com-1.3.0.dist-info/RECORD
