Metadata-Version: 2.1
Name: network_com
Version: 1.3.0
Summary: A package for client-server communication over TCP and UDP with SSL/TLS encryption
Home-page: https://github.com/KaramBelmoujoud/Multi-Client-TCP-UDP-Communication-Server-in-Python
Author: Karam Belmoujoud
Author-email: karam.bd.kb@gmail.com
Classifier: Programming Language :: Python :: 3
Classifier: License :: OSI Approved :: MIT License
Classifier: Operating System :: OS Independent
Requires-Python: >=3.6
License-File: LICENSE
Requires-Dist: inputimeout
